aimysearch/__init__.py
aimysearch/search.py
aimysearch-0.1.dist-info/LICENSE.txt
aimysearch-0.1.dist-info/METADATA
aimysearch-0.1.dist-info/WHEEL
aimysearch-0.1.dist-info/top_level.txt
aimysearch-0.1.dist-info/RECORD
