Metadata-Version: 2.1
Name: aimysearch
Version: 0.1
Summary: fussy search for any languages.
Home-page: https://github.com/egusahiroaki/aimysearch
Author: egusahiroaki
Author-email: egusa.hiroaki@gmail.com
License: UNKNOWN
Platform: UNKNOWN
Classifier: Programming Language :: Python :: 3.7
Classifier: License :: OSI Approved :: MIT License
Classifier: Topic :: Software Development :: Libraries :: Python Modules
